src/__init__.py
src/checks.py
src/client.py
src/creds.py
src/errors.py
gervasebots-0.0.2.dist-info/LICENCE
gervasebots-0.0.2.dist-info/METADATA
gervasebots-0.0.2.dist-info/WHEEL
gervasebots-0.0.2.dist-info/entry_points.txt
gervasebots-0.0.2.dist-info/top_level.txt
gervasebots-0.0.2.dist-info/RECORD
