Metadata-Version: 2.1
Name: gervasebots
Version: 0.0.2
License-File: LICENCE
Requires-Dist: requests
